sensoglove/__init__.py
sensoglove/fingers.py
sensoglove/hand.py
sensoglove/helpers.py
sensoglove/palm.py
sensoglove/rotation.py
sensoglove/sensoglove.py
sensoglove/wrist.py
sensoglove-0.2.dist-info/METADATA
sensoglove-0.2.dist-info/RECORD
sensoglove-0.2.dist-info/WHEEL
sensoglove-0.2.dist-info/top_level.txt
