Metadata-Version: 2.1
Name: sensoglove
Version: 0.2
Summary: Wrapper module for senso gloves
Home-page: https://github.com/TheRizzen/sensoglove
Author: Thibault Miranda de Oliveira
Author-email: thibault@mirandadeoliveira.com
License: MIT
Platform: UNKNOWN
Classifier: Programming Language :: Python :: 3
Classifier: License :: OSI Approved :: MIT License
Classifier: Operating System :: OS Independent
